seanox_ai_nlp/__init__.py
seanox_ai_nlp/synthetics/README.md
seanox_ai_nlp/synthetics/__init__.py
seanox_ai_nlp/synthetics/synthetics.py
seanox_ai_nlp/units/README.md
seanox_ai_nlp/units/__init__.py
seanox_ai_nlp/units/units.py
seanox_ai_nlp/units/units.xlsx
seanox_ai_nlp-1.3.0.1.dist-info/METADATA
seanox_ai_nlp-1.3.0.1.dist-info/WHEEL
seanox_ai_nlp-1.3.0.1.dist-info/licenses/LICENSE
seanox_ai_nlp-1.3.0.1.dist-info/RECORD
