Metadata-Version: 2.4
Name: seanox-ai-nlp
Version: 1.3.0.1
Summary: Lightweight NLP components for semantic processing of domain-specific content.
Project-URL: Homepage, https://github.com/seanox/seanox-ai-nlp
Project-URL: Issues, https://github.com/seanox/seanox-ai-nlp/issues
Author: Seanox Software Solutions
License: Apache-2.0
License-File: LICENSE
Keywords: NLP,data annotation,data generation,domain-specific,entity extraction,fine-tuning,information extraction,information retrieval,measurement extraction,measurement units,preprocessing,pretraining data,retrieval optimization,semantic labeling,semantic processing,semantic retrieval,sentence generator,structured data,synthetic data,synthetic text,template engine,text processing,training data augmentation
Classifier: Development Status :: 5 - Production/Stable
Classifier: Intended Audience :: Developers
Classifier: License :: OSI Approved :: Apache Software License
Classifier: Natural Language :: English
Classifier: Operating System :: OS Independent
Classifier: Programming Language :: Python :: 3
Classifier: Programming Language :: Python :: 3.10
Classifier: Programming Language :: Python :: 3.11
Classifier: Programming Language :: Python :: 3.12
Classifier: Programming Language :: Python :: 3.13
Classifier: Topic :: Scientific/Engineering :: Artificial Intelligence
Classifier: Topic :: Software Development :: Libraries :: Python Modules
Classifier: Topic :: Text Processing :: Linguistic
Requires-Python: >=3.10
Requires-Dist: jinja2>=3.0.0
Requires-Dist: jsonschema>=4.17
Requires-Dist: pyyaml>=6.0
